shipyard_googledrive/__init__.py
shipyard_googledrive/drive_utils.py
shipyard_googledrive/googledrive.py
shipyard_googledrive/cli/__init__.py
shipyard_googledrive/cli/authtest.py
shipyard_googledrive/cli/download.py
shipyard_googledrive/cli/upload.py
alli_googledrive-0.1.0a0.dist-info/METADATA
alli_googledrive-0.1.0a0.dist-info/WHEEL
alli_googledrive-0.1.0a0.dist-info/top_level.txt
alli_googledrive-0.1.0a0.dist-info/RECORD
