Metadata-Version: 2.4
Name: alli-googledrive
Version: 0.1.0a0
Summary: A local client for connecting and working with Google Drive
Requires-Python: >=3.11
Requires-Dist: google-api-python-client>=2.140.0
Requires-Dist: google-auth>=2.33.0
Requires-Dist: google-auth-httplib2>=0.2.0
Requires-Dist: google-auth-oauthlib>=1.2.1
Requires-Dist: shipyard-bp-utils>=1.2.1
Requires-Dist: shipyard-templates>=0.9.0
